NiBuDongJsX6ZhongyibenByHetfieldjoe/README.md
NiBuDongJsX6ZhongyibenByHetfieldjoe/__init__.py
NiBuDongJsX6ZhongyibenByHetfieldjoe/__main__.py
NiBuDongJsX6ZhongyibenByHetfieldjoe/file.epub
NiBuDongJsX6ZhongyibenByHetfieldjoe/index.html
NiBuDongJsX6ZhongyibenByHetfieldjoe/css/__init__.py
NiBuDongJsX6ZhongyibenByHetfieldjoe/css/annotations.css
NiBuDongJsX6ZhongyibenByHetfieldjoe/css/main.css
NiBuDongJsX6ZhongyibenByHetfieldjoe/css/normalize.css
NiBuDongJsX6ZhongyibenByHetfieldjoe/css/popup.css
NiBuDongJsX6ZhongyibenByHetfieldjoe/font/__init__.py
NiBuDongJsX6ZhongyibenByHetfieldjoe/font/fontello.eot
NiBuDongJsX6ZhongyibenByHetfieldjoe/font/fontello.svg
NiBuDongJsX6ZhongyibenByHetfieldjoe/font/fontello.ttf
NiBuDongJsX6ZhongyibenByHetfieldjoe/font/fontello.woff
NiBuDongJsX6ZhongyibenByHetfieldjoe/img/__init__.py
NiBuDongJsX6ZhongyibenByHetfieldjoe/img/annotator-glyph-sprite.png
NiBuDongJsX6ZhongyibenByHetfieldjoe/img/annotator-icon-sprite.png
NiBuDongJsX6ZhongyibenByHetfieldjoe/img/apple-touch-icon.png
NiBuDongJsX6ZhongyibenByHetfieldjoe/img/cancelfullscreen.png
NiBuDongJsX6ZhongyibenByHetfieldjoe/img/close.png
NiBuDongJsX6ZhongyibenByHetfieldjoe/img/fullscreen.png
NiBuDongJsX6ZhongyibenByHetfieldjoe/img/loader.gif
NiBuDongJsX6ZhongyibenByHetfieldjoe/img/menu-icon.png
NiBuDongJsX6ZhongyibenByHetfieldjoe/img/save.png
NiBuDongJsX6ZhongyibenByHetfieldjoe/img/saved.png
NiBuDongJsX6ZhongyibenByHetfieldjoe/img/settings-s.png
NiBuDongJsX6ZhongyibenByHetfieldjoe/img/settings.png
NiBuDongJsX6ZhongyibenByHetfieldjoe/img/star.png
NiBuDongJsX6ZhongyibenByHetfieldjoe/js/__init__.py
NiBuDongJsX6ZhongyibenByHetfieldjoe/js/epub.js
NiBuDongJsX6ZhongyibenByHetfieldjoe/js/epub.min.js
NiBuDongJsX6ZhongyibenByHetfieldjoe/js/epub.min.map
NiBuDongJsX6ZhongyibenByHetfieldjoe/js/hooks.min.js
NiBuDongJsX6ZhongyibenByHetfieldjoe/js/hooks.min.map
NiBuDongJsX6ZhongyibenByHetfieldjoe/js/reader.js
NiBuDongJsX6ZhongyibenByHetfieldjoe/js/reader.js.map
NiBuDongJsX6ZhongyibenByHetfieldjoe/js/reader.min.js
ni_bu_dong_js_x6_zhongyiben_by_hetfieldjoe-2024.3.1.0.dist-info/METADATA
ni_bu_dong_js_x6_zhongyiben_by_hetfieldjoe-2024.3.1.0.dist-info/WHEEL
ni_bu_dong_js_x6_zhongyiben_by_hetfieldjoe-2024.3.1.0.dist-info/entry_points.txt
ni_bu_dong_js_x6_zhongyiben_by_hetfieldjoe-2024.3.1.0.dist-info/top_level.txt
ni_bu_dong_js_x6_zhongyiben_by_hetfieldjoe-2024.3.1.0.dist-info/RECORD
